advisor_core/__init__.py
advisor_core/advisor_core.py
advisor_core/grouped_routes.py
advisor_core/header.py
advisor_core/payloads.py
advisor_core/query_builder.py
advisor_core/request_handler.py
stormgeo_advisor_core-1.4.0.dist-info/licenses/LICENSE.txt
stormgeo_advisor_core-1.4.0.dist-info/METADATA
stormgeo_advisor_core-1.4.0.dist-info/WHEEL
stormgeo_advisor_core-1.4.0.dist-info/top_level.txt
stormgeo_advisor_core-1.4.0.dist-info/RECORD
