Metadata-Version: 2.4
Name: stormgeo.advisor-core
Version: 1.4.0
Summary: SDK to access the advisor core API.
Home-page: https://github.com/StormGeo/advisor-sdk
Author: climatempo
License: MIT
Project-URL: Código fonte, https://github.com/StormGeo/advisor-sdk/tree/main/python-advisor-core
License-File: LICENSE.txt
Dynamic: author
Dynamic: description
Dynamic: description-content-type
Dynamic: home-page
Dynamic: license
Dynamic: license-file
Dynamic: project-url
Dynamic: summary
